PyMangler/__init__.py
PyMangler/keygen.py
PyMangler/mangle.py
PyMangler-0.0.2.dist-info/LICENSE
PyMangler-0.0.2.dist-info/METADATA
PyMangler-0.0.2.dist-info/WHEEL
PyMangler-0.0.2.dist-info/top_level.txt
PyMangler-0.0.2.dist-info/RECORD
