Metadata-Version: 2.1
Name: PyMangler
Version: 0.0.2
Summary: PyMangler contains a pure-python "encryption" scheme that can be used to *obfuscate* and *disguise* data in situations where strong encryption is not available,and security is not necessarily top priority.
Home-page: https://github.com/Wykleph/PyMangler
Author: py-am-i
Author-email: duckpuncherirl@gmail.com
License: UNKNOWN
Platform: UNKNOWN
Classifier: Programming Language :: Python :: 3
Classifier: License :: OSI Approved :: MIT License
Classifier: Operating System :: OS Independent
